kell/__init__.py
kell/localmap.py
kell-0.0.0.dist-info/METADATA
kell-0.0.0.dist-info/WHEEL
kell-0.0.0.dist-info/top_level.txt
kell-0.0.0.dist-info/RECORD
